swe_cli-0.1.2.dist-info/licenses/LICENSE
swecli/__init__.py
swecli/__main__.py
swecli/cli.py
swecli/commands/__init__.py
swecli/commands/init_analyzer.py
swecli/commands/init_command.py
swecli/commands/init_prompt_v2.txt
swecli/commands/init_template.py
swecli/commands/stats_command.py
swecli/config/__init__.py
swecli/config/models.py
swecli/config/providers/anthropic.json
swecli/config/providers/fireworks.json
swecli/config/providers/openai.json
swecli/core/__init__.py
swecli/core/abstract/__init__.py
swecli/core/abstract/base_agent.py
swecli/core/abstract/base_manager.py
swecli/core/abstract/base_monitor.py
swecli/core/abstract/base_tool.py
swecli/core/agents/__init__.py
swecli/core/agents/compact_agent.py
swecli/core/agents/planning_agent.py
swecli/core/agents/swecli_agent.py
swecli/core/agents/components/__init__.py
swecli/core/agents/components/anthropic_adapter.py
swecli/core/agents/components/api_configuration.py
swecli/core/agents/components/http_client.py
swecli/core/agents/components/response_processing.py
swecli/core/agents/components/system_prompt.py
swecli/core/agents/components/tool_schema_builder.py
swecli/core/approval/__init__.py
swecli/core/approval/manager.py
swecli/core/approval/rules.py
swecli/core/config/__init__.py
swecli/core/context/__init__.py
swecli/core/context/indexer.py
swecli/core/context/retriever.py
swecli/core/context/token_monitor.py
swecli/core/context_management/__init__.py
swecli/core/context_management/playbook.py
swecli/core/context_management/reflection/__init__.py
swecli/core/context_management/reflection/reflector.py
swecli/core/exceptions/__init__.py
swecli/core/factories/__init__.py
swecli/core/factories/agent_factory.py
swecli/core/factories/tool_factory.py
swecli/core/interfaces/__init__.py
swecli/core/interfaces/agent_interface.py
swecli/core/interfaces/approval_interface.py
swecli/core/interfaces/config_interface.py
swecli/core/interfaces/session_interface.py
swecli/core/interfaces/tool_interface.py
swecli/core/management/__init__.py
swe_cli-0.1.2.dist-info/METADATA
swe_cli-0.1.2.dist-info/WHEEL
swe_cli-0.1.2.dist-info/entry_points.txt
swe_cli-0.1.2.dist-info/top_level.txt
swe_cli-0.1.2.dist-info/RECORD
