Metadata-Version: 2.4
Name: swe-cli
Version: 0.1.2
Summary: AI-powered command-line tool for accelerated development workflows
Author-email: SWE-CLI Team <bdqnghi@gmail.com>
Maintainer-email: SWE-CLI Team <bdqnghi@gmail.com>
License: MIT
Project-URL: Homepage, https://github.com/swe-cli/swe-cli
Project-URL: Documentation, https://github.com/swe-cli/swe-cli#readme
Project-URL: Repository, https://github.com/swe-cli/swe-cli
Project-URL: Bug Tracker, https://github.com/swe-cli/swe-cli/issues
Project-URL: Changelog, https://github.com/swe-cli/swe-cli/releases
Keywords: ai,coding-assistant,cli,developer-tools,code-generation,llm,automation,software-engineering,mcp,agentic-systems
Classifier: Development Status :: 4 - Beta
Classifier: Intended Audience :: Developers
Classifier: License :: OSI Approved :: MIT License
Classifier: Programming Language :: Python :: 3
Classifier: Programming Language :: Python :: 3.10
Classifier: Programming Language :: Python :: 3.11
Classifier: Programming Language :: Python :: 3.12
Classifier: Programming Language :: Python :: 3.13
Classifier: Topic :: Software Development :: Code Generators
Classifier: Topic :: Software Development :: Libraries :: Python Modules
Classifier: Topic :: Utilities
Classifier: Environment :: Console
Classifier: Operating System :: OS Independent
Requires-Python: >=3.9
License-File: LICENSE
Requires-Dist: pydantic>=2.12.3
Requires-Dist: rich>=14.2.0
Requires-Dist: prompt-toolkit>=3.0.52
Requires-Dist: httpx>=0.28.1
Requires-Dist: requests>=2.32.5
Requires-Dist: beautifulsoup4>=4.14.2
Requires-Dist: gitpython>=3.1.45
Requires-Dist: python-dotenv>=1.1.1
Requires-Dist: tiktoken>=0.12.0
Requires-Dist: fastmcp>=2.12.5
Requires-Dist: playwright>=1.55.0
Requires-Dist: pillow>=10.0.0
Requires-Dist: fastapi>=0.119.1
Requires-Dist: uvicorn>=0.38.0
Provides-Extra: dev
Requires-Dist: pytest>=8.4.2; extra == "dev"
Requires-Dist: pytest-asyncio>=1.2.0; extra == "dev"
Requires-Dist: black>=25.9.0; extra == "dev"
Requires-Dist: ruff>=0.14.1; extra == "dev"
Requires-Dist: mypy>=1.18.2; extra == "dev"
Dynamic: license-file
Dynamic: requires-python
